WhatSender/__init__.py
WhatSender/sender.py
WhatSender-0.1.5.dist-info/METADATA
WhatSender-0.1.5.dist-info/WHEEL
WhatSender-0.1.5.dist-info/top_level.txt
WhatSender-0.1.5.dist-info/RECORD
